setup.py
DebugHeaders.egg-info/PKG-INFO
DebugHeaders.egg-info/SOURCES.txt
DebugHeaders.egg-info/dependency_links.txt
DebugHeaders.egg-info/entry_points.txt
DebugHeaders.egg-info/requires.txt
DebugHeaders.egg-info/top_level.txt
debugheaders/__init__.py