Metadata-Version: 1.0
Name: DebugHeaders
Version: 0.1
Summary: Debug headers (and bodies) of WSGI requests and responses
Home-page: UNKNOWN
Author: Ian Bicking
Author-email: ianb@colorstudy.com
License: MIT
Keywords: wsgi debugging
Platform: UNKNOWN
Classifier: Development Status :: 4 - Beta
Classifier: Environment :: Web Environment
Classifier: Framework :: Paste
Classifier: Intended Audience :: Developers
Classifier: License :: OSI Approved :: MIT License
Classifier: Topic :: Internet :: WWW/HTTP :: WSGI
Classifier: Topic :: Internet :: WWW/HTTP :: WSGI :: Middleware
